ispyb/__init__.py
ispyb/models/__init__.py
ispyb/models/_auto_db_schema.py
ispyb/models/base.py
ispyb_models_pyispyb-1.2.6.dist-info/METADATA
ispyb_models_pyispyb-1.2.6.dist-info/WHEEL
ispyb_models_pyispyb-1.2.6.dist-info/top_level.txt
ispyb_models_pyispyb-1.2.6.dist-info/RECORD
